jupyter_notebook_toc/__init__.py
jupyter_notebook_toc/cli.py
jupyter_notebook_toc/core.py
jupyter_notebook_toc-0.2.2.dist-info/LICENSE
jupyter_notebook_toc-0.2.2.dist-info/METADATA
jupyter_notebook_toc-0.2.2.dist-info/WHEEL
jupyter_notebook_toc-0.2.2.dist-info/entry_points.txt
jupyter_notebook_toc-0.2.2.dist-info/top_level.txt
jupyter_notebook_toc-0.2.2.dist-info/RECORD
