Metadata-Version: 2.2
Name: jupyter-notebook-toc
Version: 0.2.2
Summary: A tool to generate table of contents for Jupyter notebooks
Home-page: https://github.com/Viktor-Sjoberg/jupyter-notebook-toc
Author: Viktor Sjöberg
Author-email: viktor@alfrida.se
Classifier: Development Status :: 3 - Alpha
Classifier: Intended Audience :: Developers
Classifier: Topic :: Software Development :: Libraries :: Python Modules
Classifier: License :: OSI Approved :: MIT License
Classifier: Programming Language :: Python :: 3
Classifier: Programming Language :: Python :: 3.7
Classifier: Programming Language :: Python :: 3.8
Classifier: Programming Language :: Python :: 3.9
Classifier: Programming Language :: Python :: 3.10
Requires-Python: >=3.7
License-File: LICENSE
Requires-Dist: nbformat>=5.0.0
Requires-Dist: jupyter>=1.0.0
Dynamic: author
Dynamic: author-email
Dynamic: classifier
Dynamic: description
Dynamic: description-content-type
Dynamic: home-page
Dynamic: requires-dist
Dynamic: requires-python
Dynamic: summary
